LICENSE.txt
MANIFEST.in
README.md
mathfortrand/DF1N.pyc
mathfortrand/DF1S.pyc
mathfortrand/DF2N.pyc
mathfortrand/DF2S.pyc
mathfortrand/DF3N.pyc
mathfortrand/DF3S.pyc
mathfortrand/DF4N.pyc
mathfortrand/DF4S.pyc
mathfortrand/__init__.py
mathfortrand/mathcn.pyc
mathfortrand/mathcs.pyc
mathfortrand/mathpcn.pyc
mathfortrand/mathpcs.pyc
mathfortrand/out_pl.pyc
mathfortrand.egg-info/PKG-INFO
mathfortrand.egg-info/SOURCES.txt
mathfortrand.egg-info/dependency_links.txt
mathfortrand.egg-info/top_level.txt
mathfortrand2/DF1N.pyc
mathfortrand2/DF1S.pyc
mathfortrand2/DF2N.pyc
mathfortrand2/DF2S.pyc
mathfortrand2/DF3N.pyc
mathfortrand2/DF3S.pyc
mathfortrand2/DF4N.pyc
mathfortrand2/DF4S.pyc
mathfortrand2/__init__.py
mathfortrand2/mathcn.pyc
mathfortrand2/mathcs.pyc
mathfortrand2/mathpcn.pyc
mathfortrand2/mathpcs.pyc
mathfortrand2/out_pl.pyc
mathfortrand-1.2.7.dist-info/LICENSE.txt
mathfortrand-1.2.7.dist-info/METADATA
mathfortrand-1.2.7.dist-info/WHEEL
mathfortrand-1.2.7.dist-info/top_level.txt
mathfortrand-1.2.7.dist-info/RECORD
